README.rst
setup.cfg
setup.py
FredIRC.egg-info/PKG-INFO
FredIRC.egg-info/SOURCES.txt
FredIRC.egg-info/dependency_links.txt
FredIRC.egg-info/top_level.txt
fredirc/__init__.py
fredirc/client.py
fredirc/errors.py
fredirc/handler.py
fredirc/info.py
fredirc/messages.py
fredirc/parsing.py
fredirc/processor.py
fredirc/task.py