Metadata-Version: 1.1
Name: FredIRC
Version: 0.3.0
Summary: An easy-to-use, event driven framework for IRC bots.
Home-page: https://worblehat.github.io/FredIRC
Author: Tobias Marquardt
Author-email: tm@tobix.eu
License: BSD
Download-URL: https://github.com/worblehat/FredIRC/archive/v0.3.0.tar.gz
Keywords: irc client library bot framework
Platform: UNKNOWN
Classifier: Development Status :: 4 - Beta
Classifier: Intended Audience :: Developers
Classifier: License :: OSI Approved :: BSD License
Classifier: Operating System :: OS Independent
Classifier: Programming Language :: Python :: 3
Classifier: Programming Language :: Python :: 3.3
Classifier: Programming Language :: Python :: 3.4
Classifier: Topic :: Communications :: Chat :: Internet Relay Chat
Classifier: Topic :: Software Development :: Libraries :: Python Modules
